{
  "lang":"en",
  "name":"pipeline",
  "version":"0.0.0",
  "spacy_version":">=3.5.0,<3.6.0",
  "description":"",
  "author":"",
  "email":"",
  "url":"",
  "license":"",
  "spacy_git_version":"Unknown",
  "vectors":{
    "width":0,
    "vectors":0,
    "keys":0,
    "name":null,
    "mode":"default"
  },
  "labels":{
    "transformer":[

    ],
    "ner":[
      ".",
      "BODY_SIZE",
      "DISTRIBUTION_DESCRIPTOR",
      "LIFE_STAGE",
      "SAMPLING_DEVICE"
    ]
  },
  "pipeline":[
    "transformer",
    "ner"
  ],
  "components":[
    "transformer",
    "ner"
  ],
  "disabled":[

  ],
  "performance":{
    "ents_f":0.368,
    "ents_p":0.4367088608,
    "ents_r":0.3179723502,
    "ents_per_type":{
      "DISTRIBUTION_DESCRIPTOR":{
        "p":0.4701492537,
        "r":0.4846153846,
        "f":0.4772727273
      },
      "BODY_SIZE":{
        "p":0.2272727273,
        "r":0.0609756098,
        "f":0.0961538462
      },
      "LIFE_STAGE":{
        "p":0.5,
        "r":1.0,
        "f":0.6666666667
      },
      "E":{
        "p":0.0,
        "r":0.0,
        "f":0.0
      },
      "me":{
        "p":0.0,
        "r":0.0,
        "f":0.0
      },
      "l":{
        "p":0.0,
        "r":0.0,
        "f":0.0
      },
      "SAMPLING_DEVICE":{
        "p":0.0,
        "r":0.0,
        "f":0.0
      }
    },
    "transformer_loss":348.2283292414,
    "ner_loss":572.714363454
  }
}